neuromotifs/__init__.py
neuromotifs/cli.py
neuromotifs/datasets.py
neuromotifs/data/__init__.py
neuromotifs/data/nmc/__init__.py
neuromotifs/data/nmc/motifs.csv.gz
neuromotifs-0.1.0a2.dist-info/licenses/LICENSE
neuromotifs-0.1.0a2.dist-info/METADATA
neuromotifs-0.1.0a2.dist-info/WHEEL
neuromotifs-0.1.0a2.dist-info/entry_points.txt
neuromotifs-0.1.0a2.dist-info/top_level.txt
neuromotifs-0.1.0a2.dist-info/RECORD
