Metadata-Version: 2.4
Name: neuromotifs
Version: 0.1.0a2
Summary: Geometry-aware network motif analysis for neocortical microcircuits
Author: Eyal Gal, Rodrigo Perin, Henry Markram, Michael London, Idan Segev
License: MIT
Project-URL: Homepage, https://github.com/gialdetti/neuromotifs
Project-URL: Issues, https://github.com/gialdetti/neuromotifs/issues
Keywords: neuroscience,motifs,networks,geometry,microcircuit
Classifier: Development Status :: 3 - Alpha
Classifier: Intended Audience :: Science/Research
Classifier: License :: OSI Approved :: MIT License
Classifier: Programming Language :: Python :: 3
Classifier: Topic :: Scientific/Engineering :: Bio-Informatics
Requires-Python: >=3.10
License-File: LICENSE
Requires-Dist: numpy>=1.23
Requires-Dist: pandas>=1.5
Provides-Extra: dev
Requires-Dist: jupyter; extra == "dev"
Requires-Dist: ipywidgets; extra == "dev"
Requires-Dist: pytest; extra == "dev"
Dynamic: license-file
